bbanglang.py
bbanglang-0.0.0.7.dist-info/METADATA
bbanglang-0.0.0.7.dist-info/WHEEL
bbanglang-0.0.0.7.dist-info/top_level.txt
bbanglang-0.0.0.7.dist-info/RECORD
