Metadata-Version: 2.2
Name: bbanglang
Version: 0.0.0.7
Summary: erpin-bbang-lang
Home-page: https://github.com/Ilikeerpin/erpin-bbang-lang
Author: ILIKEERPIN
Author-email: ILIKEERPIN@ERPIN.com
Requires-Python: >=3.9.13
Dynamic: author
Dynamic: author-email
Dynamic: description
Dynamic: description-content-type
Dynamic: home-page
Dynamic: requires-python
Dynamic: summary
